MANIFEST.in
README.rst
setup.py
docs/HISTORY.txt
docs/LICENSE.GPL
docs/LICENSE.txt
ftw/__init__.py
ftw.participation.egg-info/PKG-INFO
ftw.participation.egg-info/SOURCES.txt
ftw.participation.egg-info/dependency_links.txt
ftw.participation.egg-info/entry_points.txt
ftw.participation.egg-info/namespace_packages.txt
ftw.participation.egg-info/not-zip-safe
ftw.participation.egg-info/requires.txt
ftw.participation.egg-info/top_level.txt
ftw/participation/__init__.py
ftw/participation/configure.zcml
ftw/participation/events.py
ftw/participation/interfaces.py
ftw/participation/invitation.py
ftw/participation/mailer.py
ftw/participation/quota.py
ftw/participation/setter.py
ftw/participation/source.py
ftw/participation/storage.py
ftw/participation/vocabularies.py
ftw/participation/activity/__init__.py
ftw/participation/activity/configure.zcml
ftw/participation/activity/renderer.py
ftw/participation/activity/subscribers.py
ftw/participation/activity/utils.py
ftw/participation/activity/templates/invitation.pt
ftw/participation/browser/__init__.py
ftw/participation/browser/accept.py
ftw/participation/browser/active.py
ftw/participation/browser/changeroles.py
ftw/participation/browser/configure.zcml
ftw/participation/browser/invitations.pt
ftw/participation/browser/invitations.py
ftw/participation/browser/invite.py
ftw/participation/browser/participants-tab.py
ftw/participation/browser/participants.pt
ftw/participation/browser/participants.py
ftw/participation/browser/participants_form.pt
ftw/participation/browser/reject.py
ftw/participation/browser/retract.py
ftw/participation/browser/welcome.py
ftw/participation/browser/mail_templates/invitation_accepted_mail_html.pt
ftw/participation/browser/mail_templates/invitation_accepted_mail_text.pt
ftw/participation/browser/mail_templates/invitation_mail_html.pt
ftw/participation/browser/mail_templates/invitation_mail_text.pt
ftw/participation/browser/mail_templates/invitation_rejected_mail_html.pt
ftw/participation/browser/mail_templates/invitation_rejected_mail_text.pt
ftw/participation/browser/resources/select_all.js
ftw/participation/locales/ftw.activity.pot
ftw/participation/locales/ftw.participation.pot
ftw/participation/locales/ftw.tabbedview.pot
ftw/participation/locales/de/LC_MESSAGES/ftw.activity.po
