Metadata-Version: 1.1
Name: ftw.participation
Version: 1.5.2
Summary: Invite other users (registered or unregistered) to a context in plone.
Home-page: https://github.com/4teamwork/ftw.participation
Author: Jonas Baumann
Author-email: mailto:info@4teamwork.ch
License: GPL2
Keywords: ftw participation plone
Platform: UNKNOWN
Classifier: Framework :: Plone
Classifier: Framework :: Plone :: 4.3
Classifier: Programming Language :: Python
Classifier: Topic :: Software Development :: Libraries :: Python Modules
